[
    {"ID": "12345cd2", "Description": "Blue jeans"},
    {"ID": "23456ef3", "Description": "White T-shirt"},
    {"ID": "34567gh4", "Description": "Black leather jacket"},
    {"ID": "45678ij5", "Description": "Red skirt"},
    {"ID": "56789kl6", "Description": "Green sweater"},
    {"ID": "67890mn7", "Description": "Brown boots"},
    {"ID": "78901no8", "Description": "Grey hoodie"},
    {"ID": "89012pq9", "Description": "Yellow raincoat"},
    {"ID": "90123qr0", "Description": "Navy blue blazer"},
    {"ID": "01234st1", "Description": "Black dress pants"},
    {"ID": "12345uv2", "Description": "White button-up shirt"},
    {"ID": "23456wx3", "Description": "Purple maxi dress"},
    {"ID": "34567yz4", "Description": "Orange polo shirt"},
    {"ID": "45678ab5", "Description": "Pink tank top"},
    {"ID": "56789cd6", "Description": "Beige cardigan"},
    {"ID": "67890ef7", "Description": "Silver sequin dress"},
    {"ID": "78901gh8", "Description": "Gold ballet flats"},
    {"ID": "89012ij9", "Description": "Denim jacket"},
    {"ID": "90123kl0", "Description": "Striped socks"},
    {"ID": "01234mn1", "Description": "Leopard print scarf"},
    {"ID": "12345op2", "Description": "Black ankle boots"},
    {"ID": "23456qr3", "Description": "Red beanie"},
    {"ID": "34567st4", "Description": "Plaid shirt"},
    {"ID": "45678uv5", "Description": "Khaki trousers"},
    {"ID": "56789wx6", "Description": "White sneakers"},
    {"ID": "67890yz7", "Description": "Black leather belt"},
    {"ID": "78901ab8", "Description": "Floral summer dress"},
    {"ID": "89012cd9", "Description": "Blue swimming trunks"},
    {"ID": "90123ef0", "Description": "Green cargo shorts"},
    {"ID": "01234gh1", "Description": "Purple leggings"},
    {"ID": "12345ij2", "Description": "Yellow sundress"},
    {"ID": "23456kl3", "Description": "Brown fedora"},
    {"ID": "34567mn4", "Description": "Grey wool coat"},
    {"ID": "45678op5", "Description": "Black turtleneck sweater"},
    {"ID": "56789qr6", "Description": "White linen pants"},
    {"ID": "67890st7", "Description": "Red cocktail dress"},
    {"ID": "78901uv8", "Description": "Blue silk tie"},
    {"ID": "89012wx9", "Description": "Black high heels"},
    {"ID": "90123yz0", "Description": "Green bomber jacket"},
    {"ID": "01234ab1", "Description": "Pink pencil skirt"},
    {"ID": "12345cd2", "Description": "Navy jumpsuit"},
    {"ID": "23456ef3", "Description": "Beige trench coat"},
    {"ID": "34567gh4", "Description": "White baseball cap"},
    {"ID": "45678ij5", "Description": "Black swimsuit"},
    {"ID": "56789kl6", "Description": "Red gym shorts"},
    {"ID": "67890mn7", "Description": "Green yoga pants"},
    {"ID": "78901op8", "Description": "Blue cycling jersey"},
    {"ID": "89012qr9", "Description": "Grey tracksuit"},
    {"ID": "90123st0", "Description": "Black leather gloves"},
    {"ID": "01234uv1", "Description": "White golf shirt"},
    {"ID": "12345wx2", "Description": "Purple ski jacket"},
    {"ID": "23456yz3", "Description": "Orange basketball jersey"},
    {"ID": "34567ab4", "Description": "Teal sarong"},
    {"ID": "45678cd5", "Description": "Brown hiking boots"}
    

    
]